<annotation>
	<folder>dayClip2</folder>
	<filename>dayClip2--00379.jpg</filename>
	<path>C:\Users\Davi.Dias\Desktop\TCC\dataset\dayClip2\dayClip2--00379.jpg</path>
	<source>
		<database>Unknown</database>
	</source>
	<size>
		<width>1280</width>
		<height>960</height>
		<depth>3</depth>
	</size>
	<segmented>0</segmented>
	<object>
		<name>semaforo verde</name>
		<pose>Unspecified</pose>
		<truncated>0</truncated>
		<difficult>0</difficult>
		<bndbox>
			<xmin>836</xmin>
			<ymin>38</ymin>
			<xmax>878</xmax>
			<ymax>132</ymax>
		</bndbox>
	</object>
	<object>
		<name>semaforo vermelho</name>
		<pose>Unspecified</pose>
		<truncated>0</truncated>
		<difficult>0</difficult>
		<bndbox>
			<xmin>524</xmin>
			<ymin>45</ymin>
			<xmax>564</xmax>
			<ymax>137</ymax>
		</bndbox>
	</object>
</annotation>
