<annotation>
	<folder></folder>
	<filename>IMG_4168_jpeg_jpg.rf.009f2c11d686e2ec26fcb8b8c198e2d5.jpg</filename>
	<path>IMG_4168_jpeg_jpg.rf.009f2c11d686e2ec26fcb8b8c198e2d5.jpg</path>
	<source>
		<database>roboflow.com</database>
	</source>
	<size>
		<width>640</width>
		<height>640</height>
		<depth>3</depth>
	</size>
	<segmented>0</segmented>
	<object>
		<name>red</name>
		<pose>Unspecified</pose>
		<truncated>0</truncated>
		<difficult>0</difficult>
		<occluded>0</occluded>
		<bndbox>
			<xmin>127</xmin>
			<xmax>157</xmax>
			<ymin>312</ymin>
			<ymax>368</ymax>
		</bndbox>
	</object>
	<object>
		<name>red</name>
		<pose>Unspecified</pose>
		<truncated>0</truncated>
		<difficult>0</difficult>
		<occluded>0</occluded>
		<bndbox>
			<xmin>377</xmin>
			<xmax>414</xmax>
			<ymin>310</ymin>
			<ymax>388</ymax>
		</bndbox>
	</object>
	<metadata>
	</metadata>
</annotation>
