<annotation>
	<folder></folder>
	<filename>traffic-light-167-_jpg.rf.f1e4486522cdcb3e15ea0b8aa511d58d.jpg</filename>
	<path>traffic-light-167-_jpg.rf.f1e4486522cdcb3e15ea0b8aa511d58d.jpg</path>
	<source>
		<database>roboflow.com</database>
	</source>
	<size>
		<width>640</width>
		<height>640</height>
		<depth>3</depth>
	</size>
	<segmented>0</segmented>
	<object>
		<name>yellow</name>
		<pose>Unspecified</pose>
		<truncated>0</truncated>
		<difficult>0</difficult>
		<occluded>0</occluded>
		<bndbox>
			<xmin>226</xmin>
			<xmax>394</xmax>
			<ymin>151</ymin>
			<ymax>534</ymax>
		</bndbox>
	</object>
	<metadata>
	</metadata>
</annotation>
