<annotation>
	<folder></folder>
	<filename>traffic-light-720-_jpg.rf.70459a6def338098140bb6889379555e.jpg</filename>
	<path>traffic-light-720-_jpg.rf.70459a6def338098140bb6889379555e.jpg</path>
	<source>
		<database>roboflow.com</database>
	</source>
	<size>
		<width>640</width>
		<height>640</height>
		<depth>3</depth>
	</size>
	<segmented>0</segmented>
	<object>
		<name>red</name>
		<pose>Unspecified</pose>
		<truncated>0</truncated>
		<difficult>0</difficult>
		<occluded>0</occluded>
		<bndbox>
			<xmin>251</xmin>
			<xmax>578</xmax>
			<ymin>206</ymin>
			<ymax>418</ymax>
		</bndbox>
	</object>
	<metadata>
	</metadata>
</annotation>
